decorated_registry/__init__.py
decorated_registry/abstract.py
decorated_registry-0.0.2.dist-info/LICENSE
decorated_registry-0.0.2.dist-info/WHEEL
decorated_registry-0.0.2.dist-info/METADATA
decorated_registry-0.0.2.dist-info/RECORD
